gidler/__init__.py
gidler/__main__.py
gidler-0.0.2.dist-info/entry_points.txt
gidler-0.0.2.dist-info/WHEEL
gidler-0.0.2.dist-info/METADATA
gidler-0.0.2.dist-info/RECORD
