Metadata-Version: 1.2
Name: gidler
Version: 0.0.2
Summary: gidler
Home-page: https://github.com/cjrh/google-images-downloader
License: UNKNOWN
Author: Caleb Hattingh
Author-email: caleb.hattingh@gmail.com
Requires-Python: 3
Classifier: Intended Audience :: Developers
Classifier: Intended Audience :: Information Technology
Classifier: License :: OSI Approved :: Apache Software License
Classifier: Programming Language :: Python :: 3
Classifier: Topic :: Internet :: WWW/HTTP :: Indexing/Search
Classifier: Topic :: Multimedia :: Graphics
Classifier: Topic :: System :: Archiving
Classifier: Topic :: Internet :: WWW/HTTP :: Browsers
Classifier: Development Status :: 2 - Pre-Alpha
Requires-Dist: python-slugify (>=1.2)
Requires-Dist: git+https://github.com/cjrh/chromote.git@switch-to-ws4py
